oda_api/__init__.py
oda_api/api.py
oda_api/cli.py
oda_api/colors.py
oda_api/custom_formatters.py
oda_api/data_products.py
oda_api/gallery_api.py
oda_api/json.py
oda_api/misc_helpers.py
oda_api/ontology_helper.py
oda_api/pkg_info.json
oda_api/plot_tools.py
oda_api/plot_tools_utils.py
oda_api/token.py
oda_api-1.3.1.dist-info/licenses/LICENSE.rst
oda_api-1.3.1.dist-info/METADATA
oda_api-1.3.1.dist-info/WHEEL
oda_api-1.3.1.dist-info/entry_points.txt
oda_api-1.3.1.dist-info/top_level.txt
oda_api-1.3.1.dist-info/RECORD
