Metadata-Version: 2.4
Name: oda_api
Version: 1.3.1
Summary: API plugin for CDCI online data analysis
Author-email: Andrea Tramacere <contact@odahub.io>, Volodymyr Savchenko <contact@odahub.io>
Maintainer-email: Gabriele Barni <contact@odahub.io>, Denys Savchenko <contact@odahub.io>
License-Expression: MIT
Requires-Python: >=3.10
License-File: LICENSE.rst
Requires-Dist: requests
Requires-Dist: astropy>=6.1
Requires-Dist: json_tricks
Requires-Dist: matplotlib>=3.10
Requires-Dist: bokeh<3.2,>3.0
Requires-Dist: numpy>=2.0; python_full_version >= "3.11"
Requires-Dist: numpy<2.0; python_full_version < "3.11"
Requires-Dist: jsonschema
Requires-Dist: pyjwt
Requires-Dist: astroquery>=0.4.4
Requires-Dist: scipy
Requires-Dist: rdflib
Requires-Dist: puremagic
Requires-Dist: click>=8.2.1
Provides-Extra: gw
Requires-Dist: gwpy; extra == "gw"
Requires-Dist: ligo.skymap; extra == "gw"
Dynamic: license-file
